pycheckers/__init__.py
pycheckers/checkers.py
pycheckers/host.py
pycheckers-0.0.3.dist-info/METADATA
pycheckers-0.0.3.dist-info/WHEEL
pycheckers-0.0.3.dist-info/entry_points.txt
pycheckers-0.0.3.dist-info/top_level.txt
pycheckers-0.0.3.dist-info/RECORD
