Metadata-Version: 2.1
Name: pycheckers
Version: 0.0.3
Requires-Dist: graphics.py
